fabproj_manager/__init__.py
fabproj_manager/fabproj.py
fabproj_manager/modules/img/fabric_logo.png
fabproj_manager/modules/ipyCreate.py
fabproj_manager-0.1.5.dist-info/LICENSE
fabproj_manager-0.1.5.dist-info/WHEEL
fabproj_manager-0.1.5.dist-info/entry_points.txt
fabproj_manager-0.1.5.dist-info/METADATA
fabproj_manager-0.1.5.dist-info/RECORD
