Metadata-Version: 2.1
Name: fabproj-manager
Version: 0.1.5
Summary: 
Author: Devin Lane
Author-email: silvertenor@icloud.com
Requires-Python: >=3.9,<4.0
Classifier: Programming Language :: Python :: 3
Classifier: Programming Language :: Python :: 3.9
Classifier: Programming Language :: Python :: 3.10
Classifier: Programming Language :: Python :: 3.11
Requires-Dist: click (>=8.1.3,<9.0.0)
Requires-Dist: nbformat (>=5.7.3,<6.0.0)
